rtl/alu.v
module alu (
    input wire [31:0] i_a,
    input wire [31:0] i_b,
    output reg [31:0] o_y,
    input wire [2:0] i_op,
    input wire i_sub,
    input wire i_arith_shift,
    input wire [2:0] i_branch_op,
    output reg o_will_branch
);

  always @(*) begin
    case (i_op)
      3'b000: begin
        if (i_sub) o_y = $signed(i_a) - $signed(i_b);
        else o_y = $signed(i_a) + $signed(i_b);
      end
      3'b001:  o_y = i_a << i_b[4:0];
      3'b010:  o_y = ($signed(i_a) < $signed(i_b));
      3'b011:  o_y = i_a < i_b;
      3'b100:  o_y = i_a ^ i_b;
      3'b101: begin
        if(i_arith_shift) o_y = i_a >>> i_b[4:0];
        else o_y = i_a >> i_b[4:0];
      end
      3'b110: o_y = i_a | i_b ;
      3'b111: o_y = i_a & i_b;
      default: o_y = 0;
    endcase
  end

  always @(*) begin
    if (i_branch_op == 3'b000) begin
      o_will_branch = (i_a == i_b);
    end else if (i_branch_op == 3'b001) begin
      o_will_branch = !(i_a == i_b);
    end else if (i_branch_op == 3'b100) begin
      o_will_branch = ($signed(i_a) < $signed(i_b));
    end else if (i_branch_op == 3'b101) begin
      o_will_branch = ($signed(i_a) >= $signed(i_b));
    end else if (i_branch_op == 3'b110) begin
      o_will_branch = i_a < i_b;
    end else if (i_branch_op == 3'b111) begin
      o_will_branch = i_a >= i_b;
    end else begin
      o_will_branch = 0;
    end
  end

endmodule

rtl/cpu.v
module cpu (
    input wire i_clk,
    input wire i_reset,
    input wire i_wb_stb,
    input wire i_wb_ack,
    input wire i_wb_stall,
    input wire [31:0] i_wb_data,
    output reg [31:0] o_wb_data,
    output reg [31:0] o_wb_addr,
    output reg o_wb_we,
    output reg [2:0] o_wb_sel,
    output reg o_wb_stb,
    output reg o_wb_stall,
    output reg o_wb_ack
);

  parameter S_IDLE = 0;
  parameter S_REQ_MEM_READ = 1;
  parameter S_END_MEM_READ = 2;
  parameter S_EXEC = 3;
  parameter S_END_MEM_READ_INSTR = 4;
  parameter S_END_MEM_WRITE_INSTR = 5;
  parameter S_INC = 6;


  integer r_state = S_IDLE;

  reg [31:0] pc = 0;
  reg [31:0] instr = 0;

  reg [31:0] reg_file[32];

  wire [31:0] rs1 = instr[19:15];
  wire [31:0] rs2 = instr[24:20];
  wire [31:0] rd = instr[11:7];
  wire [31:0] store_instr_offset = $signed({instr[31:25], instr[11:7]});
  wire [31:0] load_instr_offset = $signed(instr[31:20]);
  wire [31:0] jalr_instr_offset = $signed({instr[31], instr[19:12], instr[20], instr[30:21], 1'b0});
  wire [31:0] branch_instr_offset = $signed({instr[31], instr[7], instr[30:25], instr[11:8], 1'b0});
  wire [31:0] u_instr_offset = {instr[31:12], 12'b0};
  wire [2:0] instr_sel = instr[14:12];
  wire [2:0] branch_op = instr[14:12];
  wire [2:0] op = instr[14:12];

  wire is_alu_imm_instr = `IS_IMM_ALU_INSTR(instr);
  wire is_alu_reg_instr = `IS_REG_ALU_INSTR(instr);
  wire is_alu_instr = is_alu_imm_instr || is_alu_reg_instr;

  wire [31:0] alu_i_a = reg_file[rs1];
  wire [31:0] alu_i_b = is_alu_imm_instr ? load_instr_offset : reg_file[rs2];

  wire alu_sub_or_arith_shift = is_alu_imm_instr ? 0 : instr[30];
  wire alu_i_sub = alu_sub_or_arith_shift;
  wire alu_i_arith_shift = alu_sub_or_arith_shift;

  wire [2:0] alu_i_op = op;
  wire [2:0] alu_i_branch_op = branch_op;

  wire [31:0] alu_o_y;
  wire alu_o_will_branch;

  alu u_alu (
      .i_a          (alu_i_a),
      .i_b          (alu_i_b),
      .i_op         (alu_i_op),
      .i_sub        (alu_i_sub),
      .i_arith_shift(alu_i_arith_shift),
      .i_branch_op  (alu_i_branch_op),
      .o_y          (alu_o_y),
      .o_will_branch(alu_o_will_branch)
  );


  initial begin
    $readmemh("reg_file.txt", reg_file);
  end

  generate
    genvar idx;
    for (idx = 0; idx < 32; idx = idx + 1) begin
      wire [31:0] reg_file_tmp;
      assign reg_file_tmp = reg_file[idx];
    end
  endgenerate



  always @(posedge i_clk) begin
    if (i_reset) begin
      $display("Resetting CPU \n");
      pc <= 0;
      instr <= 0;
      o_wb_sel <= 'b010;
      o_wb_we <= 0;
      o_wb_ack <= 0;
      o_wb_stb <= 0;
      o_wb_data <= 0;
      o_wb_addr <= 0;
      o_wb_stall <= 0;
      r_state <= S_IDLE;
    end else if (r_state == S_IDLE) begin
      o_wb_ack <= 0;
      if (i_wb_stb && !o_wb_stall) begin
        o_wb_stall <= 1;
        r_state <= S_REQ_MEM_READ;
      end
    end else if (r_state == S_REQ_MEM_READ) begin
      if (!i_wb_stall) begin
        $display("cpu requeseted read from mem");
        o_wb_addr <= pc;
        o_wb_we   <= 0;
        o_wb_stb  <= 1;
        r_state   <= S_END_MEM_READ;
      end
    end else if (r_state == S_END_MEM_READ) begin
      o_wb_stb <= 0;
      if (i_wb_ack) begin
        $display("cpu fetched instr %h from addr %h", i_wb_data, o_wb_addr);
        o_wb_addr <= 0;
        o_wb_we <= 0;
        instr <= i_wb_data;
        r_state <= S_EXEC;
      end

    end else if (r_state == S_EXEC) begin
      $display("current pc is %h", pc);
      // mem read instr
      if (`IS_MEM_READ_INSTR(instr)) begin
        if (!i_wb_stall) begin
          $display("cpu requested read instr");
          o_wb_addr <= reg_file[rs1] + load_instr_offset;
          o_wb_we   <= 0;
          o_wb_sel  <= instr_sel;
          o_wb_stb  <= 1;
          r_state   <= S_END_MEM_READ_INSTR;
        end
      end  //mem write instr
        else if (`IS_MEM_WRITE_INSTR(instr)) begin
        if (!i_wb_stall) begin
          $display("cpu requested write instr");
          o_wb_addr <= reg_file[rs1] + store_instr_offset;
          o_wb_data <= reg_file[rs2];
          o_wb_we   <= 1;
          o_wb_sel  <= instr_sel;
          o_wb_stb  <= 1;
          r_state   <= S_END_MEM_WRITE_INSTR;
        end
      end  //jal instr
        else if (`IS_JAL_INSTR(instr)) begin
        $display("cpu executing jal instr");
        reg_file[rd] <= pc + 4;
        pc <= pc + jalr_instr_offset - 4;  // -4 because we add it  in S_INC
        r_state <= S_INC;
      end  //jalr instr
        else if (`IS_JALR_INSTR(instr)) begin
        $display("cpu executing jalr instr");
        $display("next instr addr is %h", pc + 4);
        $display("calculated pc is %h", pc + reg_file[rs1] + load_instr_offset);
        reg_file[rd] <= pc + 4;
        pc <= pc + reg_file[rs1] + load_instr_offset - 4;  // -4 because we add it  in S_INC
        r_state <= S_INC;
      end  //branch instr
        else if (`IS_BRANCH_INSTR(instr)) begin
        $display("cpu executing branch instr");
        if (alu_o_will_branch) begin
          $display("cpu branch taken to addr %h", pc + branch_instr_offset);
          pc <= pc + branch_instr_offset - 4;  //-4 because we add it in S_INC
          r_state <= S_INC;
        end else begin
          $display("cpu branch not taken");
          r_state <= S_INC;
        end
      end else if (is_alu_instr) begin
        if (is_alu_imm_instr) $display("cpu executing alu imm instr");
        else if (is_alu_reg_instr) $display("cpu executing alu reg instr");
        else $display("ERROR");

        $display("cpu alu i_a is %h", alu_i_a);
        $display("cpu alu i_b is %h", alu_i_b);
        $display("alu op is %b", alu_i_op);
        $display("alu sub/arith shift is %b", alu_sub_or_arith_shift);
        $display("cpu alu output is %h", alu_o_y);
        $display("cpu stored result to rd x", rd);
        reg_file[rd] <= alu_o_y;
        r_state <= S_INC;
      end else if (`IS_LUI_INSTR(instr)) begin
        $display("cpu executing lui instr");
        $display("stored %h to rd x", u_instr_offset, rd);
        reg_file[rd] <= u_instr_offset;
        r_state <= S_INC;
      end else if (`IS_AUIPC_INSTR(instr)) begin
        $display("cpu executing auipc instr");
        $display("cpu new pc is %h", pc + $signed(u_instr_offset));
        pc <= pc + $signed(u_instr_offset) - 4;
        r_state <= S_INC;
      end else begin
        $display("ERROR UNKNOWN INSTR %b at addr %h", instr, pc);
      end

    end else if (r_state == S_END_MEM_READ_INSTR) begin
      o_wb_stb <= 0;
      if (i_wb_ack) begin
        $display("cpu finished mem read instr");
        $display("read %h from addr %h to rd x", i_wb_data, o_wb_addr, rd);
        reg_file[rd] <= i_wb_data;
        o_wb_addr <= 0;
        o_wb_we <= 0;
        o_wb_sel <= 'b010;
        //o_wb_stb <= 0;
        r_state <= S_INC;
      end
    end else if (r_state == S_END_MEM_WRITE_INSTR) begin
      o_wb_stb <= 0;
      if (i_wb_ack) begin
        $display("cpu finished mem write instr");
        $display("written %h to addr %h", o_wb_data, o_wb_addr);
        o_wb_addr <= 0;
        o_wb_data <= 0;
        o_wb_we   <= 0;
        o_wb_sel  <= 'b010;
        //o_wb_stb <= 0;
        r_state   <= S_INC;
      end
    end else if (r_state == S_INC) begin
      $display("finished instr");
      $display("\n");
      pc <= pc + 4;
      o_wb_ack <= 1;
      o_wb_stall <= 0;
      r_state <= S_IDLE;
    end


  end
endmodule

rtl/mem.v
module mem (
    input wire i_clk,
    input wire i_reset,
    input wire i_wb_stb,
    input wire [31:0] i_wb_data,
    input wire [31:0] i_wb_addr,
    input wire i_wb_we,
    input wire [2:0] i_wb_sel,  //'b000- 8 bits 'b001- 16 bits 'b010- 32 bits
    output reg [31:0] o_wb_data,  //'b100 - 8 bits zero extend 'b101 - 16 bits zero extend
    output reg o_wb_ack,
    output reg o_wb_stall
);

  reg [31:0] mem_array[2**8];

  generate
    genvar idx;
    for (idx = 0; idx < 32; idx = idx + 1) begin : test_mem
      wire [31:0] tmp_mem_array;
      assign tmp_mem_array = mem_array[idx];
    end
  endgenerate

  initial $readmemh("example_program.txt", mem_array);  //Assuming name of txt is data.txt

  parameter S_IDLE = 1;
  parameter S_READ = 2;
  parameter S_WRITE = 3;


  integer r_state = S_IDLE;

  wire [31:0] word_addr;
  assign word_addr = i_wb_addr >> 2;  // division by 4


  always @(posedge i_clk) begin
    if (i_reset) begin
      r_state <= S_IDLE;
      o_wb_ack <= 0;
      o_wb_data <= 0;
      o_wb_stall <= 0;
    end
    if (r_state == S_IDLE) begin
      o_wb_ack  <= 0;
      o_wb_stall <= 0;
      o_wb_data <= 32'hFFFFFFFF;
      if (i_wb_stb && !o_wb_stall && i_wb_we) begin
        o_wb_stall  <= 1;
        r_state <= S_WRITE;
        $display("mem wil begin write");
      end else if (i_wb_stb && !o_wb_stall && !i_wb_we) begin
        o_wb_stall  <= 1;
        r_state <= S_READ;
        $display("mem will begin read");
      end
    end else if (r_state == S_WRITE) begin
      if (i_wb_sel == 'b000) begin
        mem_array[word_addr][7:0] <= i_wb_data[7:0];
      end else if (i_wb_sel == 'b001) begin
        mem_array[word_addr][15:0] <= i_wb_data[15:0];
      end else if (i_wb_sel == 'b010) begin
        mem_array[word_addr] <= i_wb_data;
      end else begin
        $display("ERROR IN MEM, INVALID SEL");
      end
      o_wb_data  <= 32'hFFFFFFFF;
      o_wb_ack   <= 1;
      //o_wb_stall <= 0;
      r_state <= S_IDLE;
      $display("finished mem wrote %h to addr %h ",i_wb_data,i_wb_addr);
    end else if (r_state == S_READ) begin
      if (i_wb_sel == 'b000) begin
        o_wb_data <= $signed(mem_array[word_addr][7:0]);
      end else if (i_wb_sel == 'b001) begin
        o_wb_data <= $signed(mem_array[word_addr][15:0]);
      end else if (i_wb_sel == 'b010) begin
        o_wb_data <= mem_array[word_addr];
      end else if (i_wb_sel == 'b100) begin
        o_wb_data <= {24'b0, mem_array[word_addr][7:0]};
      end else if (i_wb_sel == 'b101) begin
        o_wb_data <= {16'b0, mem_array[word_addr][15:0]};
      end else begin
        $display("ERROR IN MEM, INVALID SEL");
      end
      $display("finished mem outputted %h from addr %h",mem_array[word_addr],i_wb_addr);
      o_wb_ack   <= 1;
      //o_wb_stall <= 0;
      r_state <= S_IDLE;
    end else begin
      $display("ERROR INVALID STATE IN MEMORY");
    end
  end

endmodule

rtl/top_tb.v
`default_nettype none

module tb_top;

  reg clk = 0;
  reg reset = 1;
  wire mem_i_wb_stb;
  wire [31:0] mem_i_wb_data;
  wire [31:0] mem_i_wb_addr;
  wire mem_i_wb_we;
  wire [31:0] mem_o_wb_data;
  wire mem_o_wb_ack;
  wire [2:0] mem_i_wb_sel;
  wire mem_o_wb_stall;

  mem u_mem (
      .i_clk  (clk),
      .i_reset(reset),
      .i_wb_stb (mem_i_wb_stb),
      .i_wb_data (mem_i_wb_data),
      .i_wb_addr (mem_i_wb_addr),
      .i_wb_sel  (mem_i_wb_sel),
      .i_wb_we   (mem_i_wb_we),
      .o_wb_data (mem_o_wb_data),
      .o_wb_ack  (mem_o_wb_ack),
      .o_wb_stall (mem_o_wb_stall)
  );

  wire cpu_o_wb_ack;
  wire cpu_i_wb_stb;
  assign cpu_i_wb_stb = 1;

  cpu u_cpu (
      .i_clk     (clk),
      .i_reset   (reset),
      .i_wb_stb  (cpu_i_wb_stb),
      .i_wb_ack  (mem_o_wb_ack),
      .i_wb_stall(mem_o_wb_stall),
      .i_wb_data (mem_o_wb_data),
      .o_wb_data (mem_i_wb_data),
      .o_wb_addr (mem_i_wb_addr),
      .o_wb_we   (mem_i_wb_we),
      .o_wb_stb  (mem_i_wb_stb),
      .o_wb_sel  (mem_i_wb_sel),
      .o_wb_ack  (cpu_o_wb_ack)
  );



  localparam CLK_PERIOD = 10;
  always #(CLK_PERIOD / 2) clk = ~clk;

  initial begin
    $dumpfile("tb_top.vcd");
    $dumpvars(0, tb_top);
  end

  initial begin
    #10 reset <= 0;
    #1000 $finish;
  end

endmodule
`default_nettype wire

tb_top.vcd
$date
	Wed Oct 16 07:48:14 2024
$end
$version
	Icarus Verilog
$end
$timescale
	1s
$end
$scope module tb_top $end
$var wire 1 ! cpu_i_wb_stb $end
$var wire 1 " mem_o_wb_stall $end
$var wire 32 # mem_o_wb_data [31:0] $end
$var wire 1 $ mem_o_wb_ack $end
$var wire 1 % mem_i_wb_we $end
$var wire 1 & mem_i_wb_stb $end
$var wire 3 ' mem_i_wb_sel [2:0] $end
$var wire 32 ( mem_i_wb_data [31:0] $end
$var wire 32 ) mem_i_wb_addr [31:0] $end
$var wire 1 * cpu_o_wb_ack $end
$var parameter 32 + CLK_PERIOD $end
$var reg 1 , clk $end
$var reg 1 - reset $end
$scope module u_cpu $end
$var wire 32 . alu_i_a [31:0] $end
$var wire 1 / alu_i_arith_shift $end
$var wire 3 0 alu_i_branch_op [2:0] $end
$var wire 3 1 alu_i_op [2:0] $end
$var wire 1 2 alu_i_sub $end
$var wire 1 , i_clk $end
$var wire 1 - i_reset $end
$var wire 1 ! i_wb_stb $end
$var wire 1 3 is_alu_instr $end
$var wire 32 4 u_instr_offset [31:0] $end
$var wire 32 5 store_instr_offset [31:0] $end
$var wire 32 6 rs2 [31:0] $end
$var wire 32 7 rs1 [31:0] $end
$var wire 32 8 rd [31:0] $end
$var wire 3 9 op [2:0] $end
$var wire 32 : load_instr_offset [31:0] $end
$var wire 32 ; jalr_instr_offset [31:0] $end
$var wire 1 < is_alu_reg_instr $end
$var wire 1 = is_alu_imm_instr $end
$var wire 3 > instr_sel [2:0] $end
$var wire 1 " i_wb_stall $end
$var wire 32 ? i_wb_data [31:0] $end
$var wire 1 $ i_wb_ack $end
$var wire 3 @ branch_op [2:0] $end
$var wire 32 A branch_instr_offset [31:0] $end
$var wire 1 B alu_sub_or_arith_shift $end
$var wire 32 C alu_o_y [31:0] $end
$var wire 1 D alu_o_will_branch $end
$var wire 32 E alu_i_b [31:0] $end
$var parameter 32 F S_END_MEM_READ $end
$var parameter 32 G S_END_MEM_READ_INSTR $end
$var parameter 32 H S_END_MEM_WRITE_INSTR $end
$var parameter 32 I S_EXEC $end
$var parameter 32 J S_IDLE $end
$var parameter 32 K S_INC $end
$var parameter 32 L S_REQ_MEM_READ $end
$var reg 32 M instr [31:0] $end
$var reg 1 * o_wb_ack $end
$var reg 32 N o_wb_addr [31:0] $end
$var reg 32 O o_wb_data [31:0] $end
$var reg 3 P o_wb_sel [2:0] $end
$var reg 1 Q o_wb_stall $end
$var reg 1 & o_wb_stb $end
$var reg 1 % o_wb_we $end
$var reg 32 R pc [31:0] $end
$var integer 32 S r_state [31:0] $end
$scope begin genblk1[0] $end
$var wire 32 T reg_file_tmp [31:0] $end
$var parameter 2 U idx $end
$upscope $end
$scope begin genblk1[1] $end
$var wire 32 V reg_file_tmp [31:0] $end
$var parameter 2 W idx $end
$upscope $end
$scope begin genblk1[2] $end
$var wire 32 X reg_file_tmp [31:0] $end
$var parameter 3 Y idx $end
$upscope $end
$scope begin genblk1[3] $end
$var wire 32 Z reg_file_tmp [31:0] $end
$var parameter 3 [ idx $end
$upscope $end
$scope begin genblk1[4] $end
$var wire 32 \ reg_file_tmp [31:0] $end
$var parameter 4 ] idx $end
$upscope $end
$scope begin genblk1[5] $end
$var wire 32 ^ reg_file_tmp [31:0] $end
$var parameter 4 _ idx $end
$upscope $end
$scope begin genblk1[6] $end
$var wire 32 ` reg_file_tmp [31:0] $end
$var parameter 4 a idx $end
$upscope $end
$scope begin genblk1[7] $end
$var wire 32 b reg_file_tmp [31:0] $end
$var parameter 4 c idx $end
$upscope $end
$scope begin genblk1[8] $end
$var wire 32 d reg_file_tmp [31:0] $end
$var parameter 5 e idx $end
$upscope $end
$scope begin genblk1[9] $end
$var wire 32 f reg_file_tmp [31:0] $end
$var parameter 5 g idx $end
$upscope $end
$scope begin genblk1[10] $end
$var wire 32 h reg_file_tmp [31:0] $end
$var parameter 5 i idx $end
$upscope $end
$scope begin genblk1[11] $end
$var wire 32 j reg_file_tmp [31:0] $end
$var parameter 5 k idx $end
$upscope $end
$scope begin genblk1[12] $end
$var wire 32 l reg_file_tmp [31:0] $end
$var parameter 5 m idx $end
$upscope $end
$scope begin genblk1[13] $end
$var wire 32 n reg_file_tmp [31:0] $end
$var parameter 5 o idx $end
$upscope $end
$scope begin genblk1[14] $end
$var wire 32 p reg_file_tmp [31:0] $end
$var parameter 5 q idx $end
$upscope $end
$scope begin genblk1[15] $end
$var wire 32 r reg_file_tmp [31:0] $end
$var parameter 5 s idx $end
$upscope $end
$scope begin genblk1[16] $end
$var wire 32 t reg_file_tmp [31:0] $end
$var parameter 6 u idx $end
$upscope $end
$scope begin genblk1[17] $end
$var wire 32 v reg_file_tmp [31:0] $end
$var parameter 6 w idx $end
$upscope $end
$scope begin genblk1[18] $end
$var wire 32 x reg_file_tmp [31:0] $end
$var parameter 6 y idx $end
$upscope $end
$scope begin genblk1[19] $end
$var wire 32 z reg_file_tmp [31:0] $end
$var parameter 6 { idx $end
$upscope $end
$scope begin genblk1[20] $end
$var wire 32 | reg_file_tmp [31:0] $end
$var parameter 6 } idx $end
$upscope $end
$scope begin genblk1[21] $end
$var wire 32 ~ reg_file_tmp [31:0] $end
$var parameter 6 !" idx $end
$upscope $end
$scope begin genblk1[22] $end
$var wire 32 "" reg_file_tmp [31:0] $end
$var parameter 6 #" idx $end
$upscope $end
$scope begin genblk1[23] $end
$var wire 32 $" reg_file_tmp [31:0] $end
$var parameter 6 %" idx $end
$upscope $end
$scope begin genblk1[24] $end
$var wire 32 &" reg_file_tmp [31:0] $end
$var parameter 6 '" idx $end
$upscope $end
$scope begin genblk1[25] $end
$var wire 32 (" reg_file_tmp [31:0] $end
$var parameter 6 )" idx $end
$upscope $end
$scope begin genblk1[26] $end
$var wire 32 *" reg_file_tmp [31:0] $end
$var parameter 6 +" idx $end
$upscope $end
$scope begin genblk1[27] $end
$var wire 32 ," reg_file_tmp [31:0] $end
$var parameter 6 -" idx $end
$upscope $end
$scope begin genblk1[28] $end
$var wire 32 ." reg_file_tmp [31:0] $end
$var parameter 6 /" idx $end
$upscope $end
$scope begin genblk1[29] $end
$var wire 32 0" reg_file_tmp [31:0] $end
$var parameter 6 1" idx $end
$upscope $end
$scope begin genblk1[30] $end
$var wire 32 2" reg_file_tmp [31:0] $end
$var parameter 6 3" idx $end
$upscope $end
$scope begin genblk1[31] $end
$var wire 32 4" reg_file_tmp [31:0] $end
$var parameter 6 5" idx $end
$upscope $end
$scope module u_alu $end
$var wire 32 6" i_a [31:0] $end
$var wire 1 / i_arith_shift $end
$var wire 32 7" i_b [31:0] $end
$var wire 3 8" i_branch_op [2:0] $end
$var wire 3 9" i_op [2:0] $end
$var wire 1 2 i_sub $end
$var reg 1 D o_will_branch $end
$var reg 32 :" o_y [31:0] $end
$upscope $end
$upscope $end
$scope module u_mem $end
$var wire 1 , i_clk $end
$var wire 1 - i_reset $end
$var wire 32 ;" i_wb_addr [31:0] $end
$var wire 32 <" i_wb_data [31:0] $end
$var wire 3 =" i_wb_sel [2:0] $end
$var wire 1 & i_wb_stb $end
$var wire 1 % i_wb_we $end
$var wire 32 >" word_addr [31:0] $end
$var parameter 32 ?" S_IDLE $end
$var parameter 32 @" S_READ $end
$var parameter 32 A" S_WRITE $end
$var reg 1 $ o_wb_ack $end
$var reg 32 B" o_wb_data [31:0] $end
$var reg 1 " o_wb_stall $end
$var integer 32 C" r_state [31:0] $end
$scope begin test_mem[0] $end
$var wire 32 D" tmp_mem_array [31:0] $end
$var parameter 2 E" idx $end
$upscope $end
$scope begin test_mem[1] $end
$var wire 32 F" tmp_mem_array [31:0] $end
$var parameter 2 G" idx $end
$upscope $end
$scope begin test_mem[2] $end
$var wire 32 H" tmp_mem_array [31:0] $end
$var parameter 3 I" idx $end
$upscope $end
$scope begin test_mem[3] $end
$var wire 32 J" tmp_mem_array [31:0] $end
$var parameter 3 K" idx $end
$upscope $end
$scope begin test_mem[4] $end
$var wire 32 L" tmp_mem_array [31:0] $end
$var parameter 4 M" idx $end
$upscope $end
$scope begin test_mem[5] $end
$var wire 32 N" tmp_mem_array [31:0] $end
$var parameter 4 O" idx $end
$upscope $end
$scope begin test_mem[6] $end
$var wire 32 P" tmp_mem_array [31:0] $end
$var parameter 4 Q" idx $end
$upscope $end
$scope begin test_mem[7] $end
$var wire 32 R" tmp_mem_array [31:0] $end
$var parameter 4 S" idx $end
$upscope $end
$scope begin test_mem[8] $end
$var wire 32 T" tmp_mem_array [31:0] $end
$var parameter 5 U" idx $end
$upscope $end
$scope begin test_mem[9] $end
$var wire 32 V" tmp_mem_array [31:0] $end
$var parameter 5 W" idx $end
$upscope $end
$scope begin test_mem[10] $end
$var wire 32 X" tmp_mem_array [31:0] $end
$var parameter 5 Y" idx $end
$upscope $end
$scope begin test_mem[11] $end
$var wire 32 Z" tmp_mem_array [31:0] $end
$var parameter 5 [" idx $end
$upscope $end
$scope begin test_mem[12] $end
$var wire 32 \" tmp_mem_array [31:0] $end
$var parameter 5 ]" idx $end
$upscope $end
$scope begin test_mem[13] $end
$var wire 32 ^" tmp_mem_array [31:0] $end
$var parameter 5 _" idx $end
$upscope $end
$scope begin test_mem[14] $end
$var wire 32 `" tmp_mem_array [31:0] $end
$var parameter 5 a" idx $end
$upscope $end
$scope begin test_mem[15] $end
$var wire 32 b" tmp_mem_array [31:0] $end
$var parameter 5 c" idx $end
$upscope $end
$scope begin test_mem[16] $end
$var wire 32 d" tmp_mem_array [31:0] $end
$var parameter 6 e" idx $end
$upscope $end
$scope begin test_mem[17] $end
$var wire 32 f" tmp_mem_array [31:0] $end
$var parameter 6 g" idx $end
$upscope $end
$scope begin test_mem[18] $end
$var wire 32 h" tmp_mem_array [31:0] $end
$var parameter 6 i" idx $end
$upscope $end
$scope begin test_mem[19] $end
$var wire 32 j" tmp_mem_array [31:0] $end
$var parameter 6 k" idx $end
$upscope $end
$scope begin test_mem[20] $end
$var wire 32 l" tmp_mem_array [31:0] $end
$var parameter 6 m" idx $end
$upscope $end
$scope begin test_mem[21] $end
$var wire 32 n" tmp_mem_array [31:0] $end
$var parameter 6 o" idx $end
$upscope $end
$scope begin test_mem[22] $end
$var wire 32 p" tmp_mem_array [31:0] $end
$var parameter 6 q" idx $end
$upscope $end
$scope begin test_mem[23] $end
$var wire 32 r" tmp_mem_array [31:0] $end
$var parameter 6 s" idx $end
$upscope $end
$scope begin test_mem[24] $end
$var wire 32 t" tmp_mem_array [31:0] $end
$var parameter 6 u" idx $end
$upscope $end
$scope begin test_mem[25] $end
$var wire 32 v" tmp_mem_array [31:0] $end
$var parameter 6 w" idx $end
$upscope $end
$scope begin test_mem[26] $end
$var wire 32 x" tmp_mem_array [31:0] $end
$var parameter 6 y" idx $end
$upscope $end
$scope begin test_mem[27] $end
$var wire 32 z" tmp_mem_array [31:0] $end
$var parameter 6 {" idx $end
$upscope $end
$scope begin test_mem[28] $end
$var wire 32 |" tmp_mem_array [31:0] $end
$var parameter 6 }" idx $end
$upscope $end
$scope begin test_mem[29] $end
$var wire 32 ~" tmp_mem_array [31:0] $end
$var parameter 6 !# idx $end
$upscope $end
$scope begin test_mem[30] $end
$var wire 32 "# tmp_mem_array [31:0] $end
$var parameter 6 ## idx $end
$upscope $end
$scope begin test_mem[31] $end
$var wire 32 $# tmp_mem_array [31:0] $end
$var parameter 6 %# idx $end
$upscope $end
$upscope $end
$upscope $end
$enddefinitions $end
$comment Show the parameter values. $end
$dumpall
b11111 %#
b11110 ##
b11101 !#
b11100 }"
b11011 {"
b11010 y"
b11001 w"
b11000 u"
b10111 s"
b10110 q"
b10101 o"
b10100 m"
b10011 k"
b10010 i"
b10001 g"
b10000 e"
b1111 c"
b1110 a"
b1101 _"
b1100 ]"
b1011 ["
b1010 Y"
b1001 W"
b1000 U"
b111 S"
b110 Q"
b101 O"
b100 M"
b11 K"
b10 I"
b1 G"
b0 E"
b11 A"
b10 @"
b1 ?"
b11111 5"
b11110 3"
b11101 1"
b11100 /"
b11011 -"
b11010 +"
b11001 )"
b11000 '"
b10111 %"
b10110 #"
b10101 !"
b10100 }
b10011 {
b10010 y
b10001 w
b10000 u
b1111 s
b1110 q
b1101 o
b1100 m
b1011 k
b1010 i
b1001 g
b1000 e
b111 c
b110 a
b101 _
b100 ]
b11 [
b10 Y
b1 W
b0 U
b1 L
b110 K
b0 J
b11 I
b101 H
b100 G
b10 F
b1010 +
$end
#0
$dumpvars
bx $#
bx "#
bx ~"
bx |"
bx z"
bx x"
bx v"
bx t"
bx r"
bx p"
bx n"
bx l"
bx j"
bx h"
bx f"
bx d"
bx b"
bx `"
bx ^"
bx \"
bx Z"
bx X"
bx V"
bx T"
bx R"
bx P"
bx N"
b1000000010001010000000010110011 L"
b1100010000010100110011 J"
b11100000000000001000010011 H"
b11111111100000000000000110010011 F"
b11010100000000000100010011 D"
b1 C"
bx B"
b0xxxxxxxxxxxxxxxxxxxxxxxxxxxxxx >"
bx ="
bx <"
bx ;"
b0 :"
b0 9"
b0 8"
b0 7"
b0 6"
b0 4"
b0 2"
b0 0"
b0 ."
b0 ,"
b0 *"
b0 ("
b0 &"
b0 $"
b0 ""
b0 ~
b0 |
b0 z
b0 x
b0 v
b0 t
b0 r
b0 p
b0 n
b0 l
b0 j
b0 h
b0 f
b0 d
b0 b
b0 `
b0 ^
b0 \
b0 Z
b1111111111111111111111111110000 X
b0 V
b0 T
b0 S
b0 R
xQ
bx P
bx O
bx N
b0 M
b0 E
1D
b0 C
0B
b0 A
b0 @
bx ?
b0 >
0=
0<
b0 ;
b0 :
b0 9
b0 8
b0 7
b0 6
b0 5
b0 4
03
02
b0 1
b0 0
0/
b0 .
1-
0,
x*
bx )
bx (
bx '
x&
x%
x$
bx #
x"
1!
$end
#5
b0 >"
0"
b11111111111111111111111111111111 #
b11111111111111111111111111111111 ?
b11111111111111111111111111111111 B"
0$
0Q
b0 )
b0 N
b0 ;"
b0 (
b0 O
b0 <"
0&
0*
0%
b10 '
b10 P
b10 ="
1,
#10
0-
0,
#15
b1 S
1Q
1,
#20
0,
#25
b10 S
1&
1,
#30
0,
#35
0&
b10 C"
1"
1,
#40
0,
#45
b1 C"
1$
b11010100000000000100010011 #
b11010100000000000100010011 ?
b11010100000000000100010011 B"
1,
#50
0,
#55
0D
b110101 C
b110101 :"
b100000110100 ;
b100010 A
b110101 E
b110101 7"
13
b10101 6
b10 8
b100010 5
b11010100000000000000000000 4
1=
b110101 :
b11 S
b11010100000000000100010011 M
b11111111111111111111111111111111 #
b11111111111111111111111111111111 ?
b11111111111111111111111111111111 B"
0"
0$
1,
#60
0,
#65
b110 S
b110101 X
1,
#70
0,
#75
b0 S
0Q
1*
b100 R
1,
#80
0,
#85
b1 S
1Q
0*
1,
#90
0,
#95
b1 >"
b10 S
1&
b100 )
b100 N
b100 ;"
1,
#100
0,
#105
b10 C"
1"
0&
1,
#110
0,
#115
b1 C"
1$
b11111111100000000000000110010011 #
b11111111100000000000000110010011 ?
b11111111100000000000000110010011 B"
1,
#120
0,
#125
b11111111111111111111111111111000 C
b11111111111111111111111111111000 :"
b11111111111100000000011111111000 ;
b11111111111111111111111111100010 A
b11000 6
b11 8
b11111111111111111111111111100011 5
b11111111111111111111111111111000 E
b11111111111111111111111111111000 7"
b11111111100000000000000000000000 4
b0 >"
b11111111111111111111111111111000 :
b11111111111111111111111111111111 #
b11111111111111111111111111111111 ?
b11111111111111111111111111111111 B"
0"
0$
b11 S
b11111111100000000000000110010011 M
b0 )
b0 N
b0 ;"
1,
#130
0,
#135
b110 S
b11111111111111111111111111111000 Z
1,
#140
0,
#145
b0 S
0Q
1*
b1000 R
1,
#150
0,
#155
b1 S
1Q
0*
1,
#160
0,
#165
b10 >"
b10 S
1&
b1000 )
b1000 N
b1000 ;"
1,
#170
0,
#175
0&
b10 C"
1"
1,
#180
0,
#185
b1 C"
1$
b11100000000000001000010011 #
b11100000000000001000010011 ?
b11100000000000001000010011 B"
1,
#190
0,
#195
b111000 C
b111000 :"
b111000 ;
b100100 A
b100 8
b100100 5
b111000 E
b111000 7"
b11100000000000000000000000 4
b0 >"
b111000 :
b11 S
b11100000000000001000010011 M
b0 )
b0 N
b0 ;"
b11111111111111111111111111111111 #
b11111111111111111111111111111111 ?
b11111111111111111111111111111111 B"
0"
0$
1,
#200
0,
#205
b110 S
b111000 \
1,
