rtl/alu.v
module alu (
    input wire [31:0] i_a,
    input wire [31:0] i_b,
    output reg [31:0] o_y,
    input wire [2:0] i_op,
    input wire i_sub,
    input wire i_arith_shift,
    input wire [2:0] i_branch_op,
    output reg o_will_branch
);

  always @(*) begin
    case (i_op)
      3'b000: begin
        if (i_sub) o_y = $signed(i_a) - $signed(i_b);
        else o_y = $signed(i_a) + $signed(i_b);
      end
      3'b001:  o_y = i_a << i_b[4:0];
      3'b010:  o_y = $signed(i_a) < $signed(i_b);
      3'b011:  o_y = i_a < i_b;
      3'b100:  o_y = i_a ^ i_b;
      3'b101: begin
        if(i_arith_shift) o_y = i_a >>> i_b[4:0];
        else o_y = i_a >> i_b[4:0];
      end
      3'b110: o_y = i_a | i_b ;
      3'b111: o_y = i_a & i_b;
      default: o_y = 0;
    endcase
  end

  always @(*) begin
    if (i_branch_op == 3'b000) begin
      o_will_branch = (i_a == i_b);
    end else if (i_branch_op == 3'b001) begin
      o_will_branch = !(i_a == i_b);
    end else if (i_branch_op == 3'b100) begin
      o_will_branch = $signed(i_a) < $signed(i_b);
    end else if (i_branch_op == 3'b101) begin
      o_will_branch = $signed(i_a) >= $signed(i_b);
    end else if (i_branch_op == 3'b110) begin
      o_will_branch = i_a < i_b;
    end else if (i_branch_op == 3'b111) begin
      o_will_branch = i_a >= i_b;
    end else begin
      o_will_branch = 0;
    end
  end

endmodule

rtl/cpu.v
module cpu (
    input wire i_clk,
    input wire i_reset,
    input wire i_exec,
    input wire i_fin,
    input wire i_busy,
    input wire [31:0] i_data,
    output reg [31:0] o_data,
    output reg [31:0] o_addr,
    output reg o_we,
    output reg [2:0] o_sel,
    output reg o_mem_exec,
    output reg o_fin

);

  parameter S_IDLE = 0;
  parameter S_REQ_MEM_READ = 1;
  parameter S_END_MEM_READ = 2;
  parameter S_EXEC = 3;
  parameter S_END_MEM_READ_INSTR = 4;
  parameter S_END_MEM_WRITE_INSTR = 5;
  parameter S_INC = 6;


  integer r_state = S_IDLE;

  reg [31:0] pc = 0;
  reg [31:0] instr = 0;

  reg [31:0] reg_file[32];

  wire [31:0] rs1 = instr[19:15];
  wire [31:0] rs2 = instr[24:20];
  wire [31:0] rd = instr[11:7];
  wire [31:0] store_instr_offset = $signed({instr[31:25], instr[11:7]});
  wire [31:0] load_instr_offset = $signed(instr[31:20]);
  wire [31:0] jalr_instr_offset = $signed({instr[31], instr[19:12], instr[20], instr[30:21], 1'b0});
  wire [31:0] branch_instr_offset = $signed({instr[31], instr[7], instr[30:25], instr[11:8], 1'b0});
  wire [31:0] u_instr_offset = {instr[31:12],12'b0};
  wire [2:0] instr_sel = instr[14:12];
  wire [2:0] branch_op = instr[14:12];
  wire [2:0] op = instr[14:12];

  wire is_alu_imm_instr = `IS_IMM_ALU_INSTR(instr);
  wire is_alu_reg_instr = `IS_REG_ALU_INSTR(instr);
  wire is_alu_instr = is_alu_imm_instr || is_alu_reg_instr;

  wire [31:0] alu_i_a = reg_file[rs1];
  wire [31:0] alu_i_b = is_alu_imm_instr ? load_instr_offset : reg_file[rs2] ;

  wire alu_sub_or_arith_shift = is_alu_imm_instr ? 0 : instr[30];
  wire alu_i_sub  = alu_sub_or_arith_shift;
  wire alu_i_arith_shift = alu_sub_or_arith_shift;

  wire [2:0] alu_i_op = op;
  wire [2:0] alu_i_branch_op = branch_op;

  wire [31:0] alu_o_y;
  wire alu_o_will_branch;

  alu u_alu(
   .i_a           (alu_i_a           ),
   .i_b           (alu_i_b           ),
   .i_op          (alu_i_op          ),
   .i_sub         (alu_i_sub         ),
   .i_arith_shift (alu_i_arith_shift ),
   .i_branch_op   (alu_i_branch_op   ),
   .o_y           (alu_o_y           ),
   .o_will_branch (alu_o_will_branch )
  );
 

  initial begin
    $readmemh("reg_file.txt", reg_file);
  end

  generate
    genvar idx;
    for (idx = 0; idx < 32; idx = idx + 1) begin
      wire [31:0] reg_file_tmp;
      assign reg_file_tmp = reg_file[idx];
    end
  endgenerate



  always @(posedge i_clk) begin
    if (i_reset) begin
      $display("Resetting CPU \n");
      pc <= 0;
      instr <= 0;
      o_sel <= 'b010;
      o_we <= 0;
      o_fin <= 0;
      o_mem_exec <= 0;
      o_data <= 0;
      o_addr <= 0;
      r_state <= S_IDLE;
    end else begin
      if (r_state == S_IDLE) begin
        o_fin <= 0;
        if (i_exec && !i_busy) begin
          r_state <= S_REQ_MEM_READ;
        end
      end else if (r_state == S_REQ_MEM_READ) begin
        if (!i_busy) begin
          //$display("cpu requeseted read from mem");
          o_addr <= pc;
          o_we <= 0;
          o_mem_exec <= 1;
          r_state <= S_END_MEM_READ;
        end
      end else if (r_state == S_END_MEM_READ) begin
        if (i_fin) begin
          $display("cpu fetched instr %h from addr %h", i_data, o_addr);
          o_addr <= 0;
          o_we <= 0;
          o_mem_exec <= 0;
          instr <= i_data;
          r_state <= S_EXEC;
        end

      end else if (r_state == S_EXEC) begin
        // mem read instr
        if (`IS_MEM_READ_INSTR(instr)) begin
          if (!i_busy) begin
            //$display("cpu requested read instr");
            o_addr <= reg_file[rs1] + load_instr_offset;
            o_we <= 0;
            o_sel <= instr_sel;
            o_mem_exec <= 1;
            r_state <= S_END_MEM_READ_INSTR;
          end
        end  //mem write instr
        else if (`IS_MEM_WRITE_INSTR(instr)) begin
          if (!i_busy) begin
            //$display("cpu requested write instr");
            o_addr <= reg_file[rs1] + store_instr_offset;
            o_data <= reg_file[rs2];
            o_we <= 1;
            o_sel <= instr_sel;
            o_mem_exec <= 1;
            r_state <= S_END_MEM_WRITE_INSTR;
          end
        end  //jal instr
        else if (`IS_JAL_INSTR(instr)) begin
          $display("cpu executing jal instr");
          reg_file[rd] <= pc + 4;
          pc <= pc + jalr_instr_offset - 4;  // -4 because we add it  in S_INC
          r_state <= S_INC;
        end  //jalr instr
        else if (`IS_JALR_INSTR(instr)) begin
          $display("cpu executing jalr instr");
          $display("next instr addr is %h", pc + 4);
          $display("calculated pc is %h", pc + reg_file[rs1] + load_instr_offset);
          reg_file[rd] <= pc + 4;
          pc <= pc + reg_file[rs1] + load_instr_offset - 4;  // -4 because we add it  in S_INC
          r_state <= S_INC;
        end  //branch instr
        else if (`IS_BRANCH_INSTR(instr)) begin
          $display("cpu executing branch instr");
          if (alu_o_will_branch) begin
            $display("cpu branch taken to addr %h", pc + branch_instr_offset);
            pc <= pc + branch_instr_offset - 4;  //-4 because we add it in S_INC
            r_state <= S_INC;
          end
          else begin
            $display("cpu branch not taken");
            r_state <= S_INC;
          end
        end else if(is_alu_instr) begin
          if(is_alu_imm_instr) $display("cpu executing alu imm instr");
          else if(is_alu_reg_instr) $display("cpu executing alu reg instr");
          else $display("ERROR");

          $display("cpu alu i_a is %h",alu_i_a);
          $display("cpu alu i_b is %h",alu_i_b);
          $display("alu op is %b",alu_i_op);
          $display("alu sub/arith shift is %b",alu_sub_or_arith_shift);
          $display("cpu alu output is %h",alu_o_y);
          $display("cpu stored result to rd %d",rd);
          reg_file[rd] <= alu_o_y;
          r_state <= S_INC;
        end else if(`IS_LUI_INSTR(instr)) begin
          $display("cpu executing lui instr");
          $display("stored %h to rd %d",u_instr_offset,rd);
          reg_file[rd] <= u_instr_offset;
          r_state <= S_INC;
        end else if (`IS_AUIPC_INSTR(instr)) begin
          $display("cpu executing auipc instr");
          $display("cpu new pc is %h",pc + $signed(u_instr_offset));
          pc <= pc + $signed(u_instr_offset) - 4;
          r_state <= S_INC;
        end else begin
          $display("ERROR UNKNOWN INSTR %b at addr %h", instr, pc);
        end

      end else if (r_state == S_END_MEM_READ_INSTR) begin
        if (i_fin) begin
          $display("cpu finished mem read instr");
          $display("read %h from addr %h to rd %d", i_data, o_addr, rd);
          reg_file[rd] <= i_data;
          o_addr <= 0;
          o_we <= 0;
          o_sel <= 'b010;
          o_mem_exec <= 0;
          r_state <= S_INC;
        end
      end else if (r_state == S_END_MEM_WRITE_INSTR) begin
        if (i_fin) begin
          $display("cpu finished mem write instr");
          $display("written %h to addr %h", o_data, o_addr);
          o_addr <= 0;
          o_data <= 0;
          o_we <= 0;
          o_sel <= 'b010;
          o_mem_exec <= 0;
          r_state <= S_INC;
        end
      end else if (r_state == S_INC) begin
        $display("finished instr");
        $display("next pc is %h", pc + 4);
        $display("\n");
        pc <= pc + 4;
        o_fin <= 1;
        r_state <= S_IDLE;
      end

    end
  end
endmodule

rtl/mem.v
module mem (
  input wire i_clk,
  input wire i_reset,
  input wire i_exec,
  input wire [31:0] i_data,
  input wire [31:0] i_addr,
  input wire i_we,
  input wire [2:0] i_sel,   //'b000- 8 bits 'b001- 16 bits 'b010- 32 bits
  output reg [31:0] o_data, //'b100 - 8 bits zero extend 'b101 - 16 bits zero extend
  output reg o_fin,
  output reg o_busy
);

reg [31:0] mem_array [2**8];

generate
  genvar idx;
  for(idx = 0; idx < 32; idx = idx+1) begin: test_mem
    wire [31:0] tmp_mem_array;
    assign tmp_mem_array = mem_array[idx];
  end
endgenerate

initial
 $readmemh("example_program.txt",mem_array); //Assuming name of txt is data.txt

parameter S_IDLE = 1;
parameter S_READ = 2;
parameter S_WRITE = 3;


integer r_state = S_IDLE;

wire [31:0] word_addr;
assign word_addr = i_addr >> 2; // division by 4


always @(posedge i_clk) begin
  if(i_reset) begin
    r_state <= S_IDLE;
    o_fin <= 0;
    o_data <= 0;
    o_busy <= 0;
  end
  if(!i_exec) begin
  end
  else begin
    if(r_state == S_IDLE) begin
      o_fin <= 0;
      o_busy <= 0;
      o_data <= 32'hF0F0F0F0;
      if(i_exec && !o_fin && i_we) begin
        o_busy <= 1;
        r_state <= S_WRITE;
        //$display("mem wil begin write");
      end
      else if(i_exec && !o_fin && !i_we) begin
        o_busy <= 1;
        r_state <= S_READ;
        //$display("mem will begin read");
      end
    end
    else if(r_state == S_WRITE) begin
      o_busy <= 1;
      if(i_sel == 'b000) begin
        mem_array[word_addr][7:0] <= i_data[7:0];
      end
      else if(i_sel == 'b001) begin
        mem_array[word_addr][15:0] <= i_data[15:0];
      end
      else if(i_sel == 'b010) begin
        mem_array[word_addr] <= i_data;
      end
      else begin
        $display("ERROR IN MEM, INVALID SEL");
      end
      o_data <= 32'hFFFFFFFF;
      o_fin <= 1;
      //o_busy <= 0;
      r_state <= S_IDLE;
      //$display("finished mem wrote %b to addr %d ",i_data,i_addr);
    end
    else if(r_state == S_READ) begin
      o_busy <= 1;
      if(i_sel == 'b000) begin
        o_data <= $signed(mem_array[word_addr][7:0]);
      end 
      else if(i_sel == 'b001) begin
        o_data <= $signed(mem_array[word_addr][15:0]);
      end
      else if(i_sel == 'b010) begin
        o_data <= mem_array[word_addr];
      end 
      else if(i_sel == 'b100) begin
        o_data <= {24'b0 , mem_array[word_addr][7:0]};
      end
      else if(i_sel == 'b101) begin
        o_data <= {16'b0, mem_array[word_addr][15:0]};
      end
      else begin
        $display("ERROR IN MEM, INVALID SEL");
      end
      //$display("finished mem outputted %b from addr %d",mem_array[word_addr],i_addr);
      o_fin <= 1;
      //o_busy <= 0;
      r_state <= S_IDLE;
    end
    else begin
      $display("ERROR INVALID STATE IN MEMORY");
    end
  end
end


endmodule

rtl/top_tb.v
`default_nettype none

module tb_top;

  reg clk = 0;
  reg reset = 1;
  wire mem_i_exec;
  wire [31:0] mem_i_data;
  wire [31:0] mem_i_addr;
  wire mem_i_we;
  wire [31:0] mem_o_data;
  wire mem_o_fin;
  wire [2:0] mem_i_sel;
  wire mem_o_busy;

  mem u_mem (
      .i_clk  (clk),
      .i_reset(reset),
      .i_exec (mem_i_exec),
      .i_data (mem_i_data),
      .i_addr (mem_i_addr),
      .i_sel  (mem_i_sel),
      .i_we   (mem_i_we),
      .o_data (mem_o_data),
      .o_fin  (mem_o_fin),
      .o_busy (mem_o_busy)
  );

  wire cpu_o_fin;
  wire cpu_i_exec;
  assign cpu_i_exec = 1;

  cpu u_cpu (
      .i_clk     (clk),
      .i_reset   (reset),
      .i_exec    (cpu_i_exec),
      .i_fin     (mem_o_fin),
      .i_busy    (mem_o_busy),
      .i_data    (mem_o_data),
      .o_data    (mem_i_data),
      .o_addr    (mem_i_addr),
      .o_we      (mem_i_we),
      .o_mem_exec(mem_i_exec),
      .o_sel     (mem_i_sel),
      .o_fin     (cpu_o_fin)
  );



  localparam CLK_PERIOD = 10;
  always #(CLK_PERIOD / 2) clk = ~clk;

  initial begin
    $dumpfile("tb_top.vcd");
    $dumpvars(0, tb_top);
  end

  initial begin
    #10 reset <= 0;
    #1000 $finish;
  end

endmodule
`default_nettype wire

tb_top.vcd
$date
	Tue Oct 15 20:02:40 2024
$end
$version
	Icarus Verilog
$end
$timescale
	1s
$end
$scope module tb_top $end
$var wire 1 ! cpu_i_exec $end
$var wire 1 " mem_o_fin $end
$var wire 32 # mem_o_data [31:0] $end
$var wire 1 $ mem_o_busy $end
$var wire 1 % mem_i_we $end
$var wire 3 & mem_i_sel [2:0] $end
$var wire 1 ' mem_i_exec $end
$var wire 32 ( mem_i_data [31:0] $end
$var wire 32 ) mem_i_addr [31:0] $end
$var wire 1 * cpu_o_fin $end
$var parameter 32 + CLK_PERIOD $end
$var reg 1 , clk $end
$var reg 1 - reset $end
$scope module u_cpu $end
$var wire 32 . alu_i_a [31:0] $end
$var wire 1 / alu_i_arith_shift $end
$var wire 3 0 alu_i_branch_op [2:0] $end
$var wire 3 1 alu_i_op [2:0] $end
$var wire 1 2 alu_i_sub $end
$var wire 1 , i_clk $end
$var wire 1 ! i_exec $end
$var wire 1 - i_reset $end
$var wire 1 3 is_alu_instr $end
$var wire 32 4 u_instr_offset [31:0] $end
$var wire 32 5 store_instr_offset [31:0] $end
$var wire 32 6 rs2 [31:0] $end
$var wire 32 7 rs1 [31:0] $end
$var wire 32 8 rd [31:0] $end
$var wire 3 9 op [2:0] $end
$var wire 32 : load_instr_offset [31:0] $end
$var wire 32 ; jalr_instr_offset [31:0] $end
$var wire 1 < is_alu_reg_instr $end
$var wire 1 = is_alu_imm_instr $end
$var wire 3 > instr_sel [2:0] $end
$var wire 1 " i_fin $end
$var wire 32 ? i_data [31:0] $end
$var wire 1 $ i_busy $end
$var wire 3 @ branch_op [2:0] $end
$var wire 32 A branch_instr_offset [31:0] $end
$var wire 1 B alu_sub_or_arith_shift $end
$var wire 32 C alu_o_y [31:0] $end
$var wire 1 D alu_o_will_branch $end
$var wire 32 E alu_i_b [31:0] $end
$var parameter 32 F S_END_MEM_READ $end
$var parameter 32 G S_END_MEM_READ_INSTR $end
$var parameter 32 H S_END_MEM_WRITE_INSTR $end
$var parameter 32 I S_EXEC $end
$var parameter 32 J S_IDLE $end
$var parameter 32 K S_INC $end
$var parameter 32 L S_REQ_MEM_READ $end
$var reg 32 M instr [31:0] $end
$var reg 32 N o_addr [31:0] $end
$var reg 32 O o_data [31:0] $end
$var reg 1 * o_fin $end
$var reg 1 ' o_mem_exec $end
$var reg 3 P o_sel [2:0] $end
$var reg 1 % o_we $end
$var reg 32 Q pc [31:0] $end
$var integer 32 R r_state [31:0] $end
$scope begin genblk1[0] $end
$var wire 32 S reg_file_tmp [31:0] $end
$var parameter 2 T idx $end
$upscope $end
$scope begin genblk1[1] $end
$var wire 32 U reg_file_tmp [31:0] $end
$var parameter 2 V idx $end
$upscope $end
$scope begin genblk1[2] $end
$var wire 32 W reg_file_tmp [31:0] $end
$var parameter 3 X idx $end
$upscope $end
$scope begin genblk1[3] $end
$var wire 32 Y reg_file_tmp [31:0] $end
$var parameter 3 Z idx $end
$upscope $end
$scope begin genblk1[4] $end
$var wire 32 [ reg_file_tmp [31:0] $end
$var parameter 4 \ idx $end
$upscope $end
$scope begin genblk1[5] $end
$var wire 32 ] reg_file_tmp [31:0] $end
$var parameter 4 ^ idx $end
$upscope $end
$scope begin genblk1[6] $end
$var wire 32 _ reg_file_tmp [31:0] $end
$var parameter 4 ` idx $end
$upscope $end
$scope begin genblk1[7] $end
$var wire 32 a reg_file_tmp [31:0] $end
$var parameter 4 b idx $end
$upscope $end
$scope begin genblk1[8] $end
$var wire 32 c reg_file_tmp [31:0] $end
$var parameter 5 d idx $end
$upscope $end
$scope begin genblk1[9] $end
$var wire 32 e reg_file_tmp [31:0] $end
$var parameter 5 f idx $end
$upscope $end
$scope begin genblk1[10] $end
$var wire 32 g reg_file_tmp [31:0] $end
$var parameter 5 h idx $end
$upscope $end
$scope begin genblk1[11] $end
$var wire 32 i reg_file_tmp [31:0] $end
$var parameter 5 j idx $end
$upscope $end
$scope begin genblk1[12] $end
$var wire 32 k reg_file_tmp [31:0] $end
$var parameter 5 l idx $end
$upscope $end
$scope begin genblk1[13] $end
$var wire 32 m reg_file_tmp [31:0] $end
$var parameter 5 n idx $end
$upscope $end
$scope begin genblk1[14] $end
$var wire 32 o reg_file_tmp [31:0] $end
$var parameter 5 p idx $end
$upscope $end
$scope begin genblk1[15] $end
$var wire 32 q reg_file_tmp [31:0] $end
$var parameter 5 r idx $end
$upscope $end
$scope begin genblk1[16] $end
$var wire 32 s reg_file_tmp [31:0] $end
$var parameter 6 t idx $end
$upscope $end
$scope begin genblk1[17] $end
$var wire 32 u reg_file_tmp [31:0] $end
$var parameter 6 v idx $end
$upscope $end
$scope begin genblk1[18] $end
$var wire 32 w reg_file_tmp [31:0] $end
$var parameter 6 x idx $end
$upscope $end
$scope begin genblk1[19] $end
$var wire 32 y reg_file_tmp [31:0] $end
$var parameter 6 z idx $end
$upscope $end
$scope begin genblk1[20] $end
$var wire 32 { reg_file_tmp [31:0] $end
$var parameter 6 | idx $end
$upscope $end
$scope begin genblk1[21] $end
$var wire 32 } reg_file_tmp [31:0] $end
$var parameter 6 ~ idx $end
$upscope $end
$scope begin genblk1[22] $end
$var wire 32 !" reg_file_tmp [31:0] $end
$var parameter 6 "" idx $end
$upscope $end
$scope begin genblk1[23] $end
$var wire 32 #" reg_file_tmp [31:0] $end
$var parameter 6 $" idx $end
$upscope $end
$scope begin genblk1[24] $end
$var wire 32 %" reg_file_tmp [31:0] $end
$var parameter 6 &" idx $end
$upscope $end
$scope begin genblk1[25] $end
$var wire 32 '" reg_file_tmp [31:0] $end
$var parameter 6 (" idx $end
$upscope $end
$scope begin genblk1[26] $end
$var wire 32 )" reg_file_tmp [31:0] $end
$var parameter 6 *" idx $end
$upscope $end
$scope begin genblk1[27] $end
$var wire 32 +" reg_file_tmp [31:0] $end
$var parameter 6 ," idx $end
$upscope $end
$scope begin genblk1[28] $end
$var wire 32 -" reg_file_tmp [31:0] $end
$var parameter 6 ." idx $end
$upscope $end
$scope begin genblk1[29] $end
$var wire 32 /" reg_file_tmp [31:0] $end
$var parameter 6 0" idx $end
$upscope $end
$scope begin genblk1[30] $end
$var wire 32 1" reg_file_tmp [31:0] $end
$var parameter 6 2" idx $end
$upscope $end
$scope begin genblk1[31] $end
$var wire 32 3" reg_file_tmp [31:0] $end
$var parameter 6 4" idx $end
$upscope $end
$scope module u_alu $end
$var wire 32 5" i_a [31:0] $end
$var wire 1 / i_arith_shift $end
$var wire 32 6" i_b [31:0] $end
$var wire 3 7" i_branch_op [2:0] $end
$var wire 3 8" i_op [2:0] $end
$var wire 1 2 i_sub $end
$var reg 1 D o_will_branch $end
$var reg 32 9" o_y [31:0] $end
$upscope $end
$upscope $end
$scope module u_mem $end
$var wire 32 :" i_addr [31:0] $end
$var wire 1 , i_clk $end
$var wire 32 ;" i_data [31:0] $end
$var wire 1 ' i_exec $end
$var wire 1 - i_reset $end
$var wire 3 <" i_sel [2:0] $end
$var wire 1 % i_we $end
$var wire 32 =" word_addr [31:0] $end
$var parameter 32 >" S_IDLE $end
$var parameter 32 ?" S_READ $end
$var parameter 32 @" S_WRITE $end
$var reg 1 $ o_busy $end
$var reg 32 A" o_data [31:0] $end
$var reg 1 " o_fin $end
$var integer 32 B" r_state [31:0] $end
$scope begin test_mem[0] $end
$var wire 32 C" tmp_mem_array [31:0] $end
$var parameter 2 D" idx $end
$upscope $end
$scope begin test_mem[1] $end
$var wire 32 E" tmp_mem_array [31:0] $end
$var parameter 2 F" idx $end
$upscope $end
$scope begin test_mem[2] $end
$var wire 32 G" tmp_mem_array [31:0] $end
$var parameter 3 H" idx $end
$upscope $end
$scope begin test_mem[3] $end
$var wire 32 I" tmp_mem_array [31:0] $end
$var parameter 3 J" idx $end
$upscope $end
$scope begin test_mem[4] $end
$var wire 32 K" tmp_mem_array [31:0] $end
$var parameter 4 L" idx $end
$upscope $end
$scope begin test_mem[5] $end
$var wire 32 M" tmp_mem_array [31:0] $end
$var parameter 4 N" idx $end
$upscope $end
$scope begin test_mem[6] $end
$var wire 32 O" tmp_mem_array [31:0] $end
$var parameter 4 P" idx $end
$upscope $end
$scope begin test_mem[7] $end
$var wire 32 Q" tmp_mem_array [31:0] $end
$var parameter 4 R" idx $end
$upscope $end
$scope begin test_mem[8] $end
$var wire 32 S" tmp_mem_array [31:0] $end
$var parameter 5 T" idx $end
$upscope $end
$scope begin test_mem[9] $end
$var wire 32 U" tmp_mem_array [31:0] $end
$var parameter 5 V" idx $end
$upscope $end
$scope begin test_mem[10] $end
$var wire 32 W" tmp_mem_array [31:0] $end
$var parameter 5 X" idx $end
$upscope $end
$scope begin test_mem[11] $end
$var wire 32 Y" tmp_mem_array [31:0] $end
$var parameter 5 Z" idx $end
$upscope $end
$scope begin test_mem[12] $end
$var wire 32 [" tmp_mem_array [31:0] $end
$var parameter 5 \" idx $end
$upscope $end
$scope begin test_mem[13] $end
$var wire 32 ]" tmp_mem_array [31:0] $end
$var parameter 5 ^" idx $end
$upscope $end
$scope begin test_mem[14] $end
$var wire 32 _" tmp_mem_array [31:0] $end
$var parameter 5 `" idx $end
$upscope $end
$scope begin test_mem[15] $end
$var wire 32 a" tmp_mem_array [31:0] $end
$var parameter 5 b" idx $end
$upscope $end
$scope begin test_mem[16] $end
$var wire 32 c" tmp_mem_array [31:0] $end
$var parameter 6 d" idx $end
$upscope $end
$scope begin test_mem[17] $end
$var wire 32 e" tmp_mem_array [31:0] $end
$var parameter 6 f" idx $end
$upscope $end
$scope begin test_mem[18] $end
$var wire 32 g" tmp_mem_array [31:0] $end
$var parameter 6 h" idx $end
$upscope $end
$scope begin test_mem[19] $end
$var wire 32 i" tmp_mem_array [31:0] $end
$var parameter 6 j" idx $end
$upscope $end
$scope begin test_mem[20] $end
$var wire 32 k" tmp_mem_array [31:0] $end
$var parameter 6 l" idx $end
$upscope $end
$scope begin test_mem[21] $end
$var wire 32 m" tmp_mem_array [31:0] $end
$var parameter 6 n" idx $end
$upscope $end
$scope begin test_mem[22] $end
$var wire 32 o" tmp_mem_array [31:0] $end
$var parameter 6 p" idx $end
$upscope $end
$scope begin test_mem[23] $end
$var wire 32 q" tmp_mem_array [31:0] $end
$var parameter 6 r" idx $end
$upscope $end
$scope begin test_mem[24] $end
$var wire 32 s" tmp_mem_array [31:0] $end
$var parameter 6 t" idx $end
$upscope $end
$scope begin test_mem[25] $end
$var wire 32 u" tmp_mem_array [31:0] $end
$var parameter 6 v" idx $end
$upscope $end
$scope begin test_mem[26] $end
$var wire 32 w" tmp_mem_array [31:0] $end
$var parameter 6 x" idx $end
$upscope $end
$scope begin test_mem[27] $end
$var wire 32 y" tmp_mem_array [31:0] $end
$var parameter 6 z" idx $end
$upscope $end
$scope begin test_mem[28] $end
$var wire 32 {" tmp_mem_array [31:0] $end
$var parameter 6 |" idx $end
$upscope $end
$scope begin test_mem[29] $end
$var wire 32 }" tmp_mem_array [31:0] $end
$var parameter 6 ~" idx $end
$upscope $end
$scope begin test_mem[30] $end
$var wire 32 !# tmp_mem_array [31:0] $end
$var parameter 6 "# idx $end
$upscope $end
$scope begin test_mem[31] $end
$var wire 32 ## tmp_mem_array [31:0] $end
$var parameter 6 $# idx $end
$upscope $end
$upscope $end
$upscope $end
$enddefinitions $end
$comment Show the parameter values. $end
$dumpall
b11111 $#
b11110 "#
b11101 ~"
b11100 |"
b11011 z"
b11010 x"
b11001 v"
b11000 t"
b10111 r"
b10110 p"
b10101 n"
b10100 l"
b10011 j"
b10010 h"
b10001 f"
b10000 d"
b1111 b"
b1110 `"
b1101 ^"
b1100 \"
b1011 Z"
b1010 X"
b1001 V"
b1000 T"
b111 R"
b110 P"
b101 N"
b100 L"
b11 J"
b10 H"
b1 F"
b0 D"
b11 @"
b10 ?"
b1 >"
b11111 4"
b11110 2"
b11101 0"
b11100 ."
b11011 ,"
b11010 *"
b11001 ("
b11000 &"
b10111 $"
b10110 ""
b10101 ~
b10100 |
b10011 z
b10010 x
b10001 v
b10000 t
b1111 r
b1110 p
b1101 n
b1100 l
b1011 j
b1010 h
b1001 f
b1000 d
b111 b
b110 `
b101 ^
b100 \
b11 Z
b10 X
b1 V
b0 T
b1 L
b110 K
b0 J
b11 I
b101 H
b100 G
b10 F
b1010 +
$end
#0
$dumpvars
bx ##
bx !#
bx }"
bx {"
bx y"
bx w"
bx u"
bx s"
bx q"
bx o"
bx m"
bx k"
bx i"
bx g"
bx e"
bx c"
bx a"
bx _"
bx ]"
bx ["
bx Y"
bx W"
bx U"
bx S"
bx Q"
bx O"
bx M"
b1000000010001010000000010110011 K"
b1100010000010100110011 I"
b11100000000000001000010011 G"
b11111111100000000000000110010011 E"
b11010100000000000100010011 C"
b1 B"
bx A"
b0xxxxxxxxxxxxxxxxxxxxxxxxxxxxxx ="
bx <"
bx ;"
bx :"
b0 9"
b0 8"
b0 7"
b0 6"
b0 5"
b0 3"
b0 1"
b0 /"
b0 -"
b0 +"
b0 )"
b0 '"
b0 %"
b0 #"
b0 !"
b0 }
b0 {
b0 y
b0 w
b0 u
b0 s
b0 q
b0 o
b0 m
b0 k
b0 i
b0 g
b0 e
b0 c
b0 a
b0 _
b0 ]
b0 [
b0 Y
b1111111111111111111111111110000 W
b0 U
b0 S
b0 R
b0 Q
bx P
bx O
bx N
b0 M
b0 E
1D
b0 C
0B
b0 A
b0 @
bx ?
b0 >
0=
0<
b0 ;
b0 :
b0 9
b0 8
b0 7
b0 6
b0 5
b0 4
03
02
b0 1
b0 0
0/
b0 .
1-
0,
x*
bx )
bx (
x'
bx &
x%
x$
bx #
x"
1!
$end
#5
b0 ="
0$
b11110000111100001111000011110000 #
b11110000111100001111000011110000 ?
b11110000111100001111000011110000 A"
0"
b0 )
b0 N
b0 :"
b0 (
b0 O
b0 ;"
0'
0*
0%
b10 &
b10 P
b10 <"
1,
#10
0-
0,
#15
b1 R
1,
#20
0,
#25
b10 R
1'
1,
#30
0,
#35
b10 B"
1$
1,
#40
0,
#45
b1 B"
1"
b11010100000000000100010011 #
b11010100000000000100010011 ?
b11010100000000000100010011 A"
1,
#50
0,
#55
0D
b110101 C
b110101 9"
b100000110100 ;
b100010 A
b110101 E
b110101 6"
13
b10101 6
b10 8
b100010 5
b11010100000000000000000000 4
1=
b110101 :
b11 R
b11010100000000000100010011 M
0'
b11110000111100001111000011110000 #
b11110000111100001111000011110000 ?
b11110000111100001111000011110000 A"
0$
0"
1,
#60
0,
#65
b110 R
b110101 W
1,
#70
0,
#75
b0 R
1*
b100 Q
1,
#80
0,
#85
b1 R
0*
1,
#90
0,
#95
b1 ="
b10 R
1'
b100 )
b100 N
b100 :"
1,
#100
0,
#105
b10 B"
1$
1,
#110
0,
#115
b1 B"
1"
b11111111100000000000000110010011 #
b11111111100000000000000110010011 ?
b11111111100000000000000110010011 A"
1,
#120
0,
#125
b11111111111111111111111111111000 C
b11111111111111111111111111111000 9"
b11111111111100000000011111111000 ;
b11111111111111111111111111100010 A
b11000 6
b11 8
b11111111111111111111111111100011 5
b11111111111111111111111111111000 E
b11111111111111111111111111111000 6"
b11111111100000000000000000000000 4
b0 ="
b11111111111111111111111111111000 :
b11110000111100001111000011110000 #
b11110000111100001111000011110000 ?
b11110000111100001111000011110000 A"
0$
0"
b11 R
b11111111100000000000000110010011 M
0'
b0 )
b0 N
b0 :"
1,
#130
0,
#135
b110 R
b11111111111111111111111111111000 Y
1,
#140
0,
#145
b0 R
1*
b1000 Q
1,
#150
0,
#155
b1 R
0*
1,
#160
0,
#165
b10 ="
b10 R
1'
b1000 )
b1000 N
b1000 :"
1,
#170
0,
#175
b10 B"
1$
1,
#180
0,
#185
b1 B"
1"
b11100000000000001000010011 #
b11100000000000001000010011 ?
b11100000000000001000010011 A"
1,
#190
0,
#195
b111000 C
b111000 9"
b111000 ;
b100100 A
b100 8
b100100 5
b111000 E
b111000 6"
b11100000000000000000000000 4
b0 ="
b111000 :
b11 R
b11100000000000001000010011 M
0'
b0 )
b0 N
b0 :"
b11110000111100001111000011110000 #
b11110000111100001111000011110000 ?
b11110000111100001111000011110000 A"
0$
0"
1,
#200
0,
#205
b110 R
b111000 [
1,
#210
0,
#215
b0 R
1*
b1100 Q
1,
#220
0,
#225
b1 R
0*
1,
#230
0,
#235
b11 ="
b10 R
1'
b1100 )
b1100 N
b1100 :"
1,
#240
0,
#245
b10 B"
1$
1,
#250
0,
#255
b1 B"
1"
b1100010000010100110011 #
b1100010000010100110011 ?
b1100010000010100110011 A"
1,
#260
0,
#265
b101101 C
b101101 9"
b10000100000000010 ;
b1010 A
b110101 .
b110101 5"
b10 7
b11 6
b1010 8
b1010 5
b11111111111111111111111111111000 E
b11111111111111111111111111111000 6"
b1100010000000000000000 4
0=
1<
b0 ="
b11 :
b11110000111100001111000011110000 #
b11110000111100001111000011110000 ?
b11110000111100001111000011110000 A"
0$
0"
b11 R
b1100010000010100110011 M
0'
b0 )
b0 N
b0 :"
1,
#270
0,
#275
b110 R
b101101 g
1,
#280
0,
#285
b0 R
1*
b10000 Q
1,
#290
0,
#295
b1 R
0*
1,
#300
0,
#305
b100 ="
b10 R
1'
b10000 )
b10000 N
b10000 :"
1,
#310
0,
#315
b10 B"
1$
1,
#320
0,
